Workbook

Sheet Planilha1
A1: RELATÓRIO DE FATURAMENTO | I1: Nº | J1: 2900
A3: DADOS DO NAVIO/PORTO
A4: Nº DO NAVIO | J4: DATA INICIAL
A5: NOME DO NAVIO | D5: BANGLAR ARJAN | J5: 46260
A6: PORTO | D6: RIO DE JANEIRO | J6: DATA FINAL
A7: LOCAL | D7: AO LARGO | J7: 46261
A9: DADOS CADASTRAIS - AGÊNCIA
A10: CNPJ | D10: 17.033.530/0004-81 | H10: INSCR. MUN. | J10: 0
A11: AGÊNCIA | D11: NORTH STAR SUDESTE SERVICOS MARITIMOS LTDA
A12: ENDEREÇO | D12: RUA DO PASSEIO, 387 SAL 1501/1504 - CENTRO
D13: CEP.: | E13: 20.021-290 | G13: CIDADE/UF: | H13: RIO DE JANEIRO/RJ
D14: TEL: | G14: E-MAIL: | H14: rio@nsshipping.com.br
A16: DESCRIÇÃO DOS CUSTOS
A17: REPASSE COM OS VIGIAS PORTUÁRIOS
A19: MMO VIGIAS | J19: =(220.52*2)+(330.79*3) -> 1433.41
A21: ENCARGOS | H21: 0.5962 | J21: =J19*H21 -> 854.59904
A23: SUB TOTAL | J23: =SUM(J19:J21) -> 2288.009
A25: ADMINISTRAÇÃO | H25: 0.9 | J25: =J23*H25 -> 2059.2081
A27: BENEFÍCIOS | D27: Períodos - Vale Transporte - Valor | G27: Períodos - Vale Refeição - Valor
D28: 5 | E28: 9.98 | F28: =D28*E28 -> 49.9 | G28: =D28 -> 5 | H28: 13.69 | I28: =G28*H28 -> 68.45 | J28: =F28+I28 -> 118.35
A30: TOTAL | J30: =J23+J25+J28 -> 4465.5672
A32: MEMÓRIA DE CÁLCULO DOS ENCARGOS
A34: PREVIDÊNCIA PATRONAL | J34: 0.2871
A36: 13º SALÁRIO | J36: 0.0909
A38: FÉRIAS | J38: 0.1212
A40: FGTS | J40: 0.097
A42: TOTAL DOS ENCARGOS | J42: =SUM(J34:J41) -> 0.5962
B44: MUITO IMPORTANTE
B45: Os pagamentos devem ser realizados somente na conta abaixo descriminada:
B46: SINDICATO DOS VIGIAS PORTUÁRIOS DO ESTADO DO RIO DE JANEIRO
B47: CNPJ: 34.160.960/0001-30
B48: CAIXA ECONÔMICA FEDERAL
B49: AG. 0209
B50: OP: 1388
B51: C/POUPANÇA: 000718677787-3

Sheet Planilha2
A1: FATURA DE SERVIÇOS | J1: Nº | K1: =Planilha1!J1 -> 2900
J2: Data: | K2: 46266
A4: PRESTADOR DE SERVIÇOS
A5: Empresa: | C5: SINDICATO DOS VIGIAS PORTUÁRIOS DO ESTADO DO RIO DE JANEIRO
A6: CNPJ: | C6: 34.160.960/0001-30 | G6: Insc. Municipal:
A7: Endereço: | C7: Rua Sacadura Cabral, 120 - salas 401 a 403 - Saúde
A8: CEP.: | C8: 20081-262 | G8: Cidade/UF: | I8: Rio de Janeiro/RJ
A9: Telefone: | C9: (21) 2263-4430 | G9: E-mail: | I9: sindvig.secretario@gmail.com
A11: TOMADOR DE SERVIÇOS
A12: Empresa: | C12: =Planilha1!D11 -> NORTH STAR SUDESTE SERVICOS MARITIMOS LTDA
A13: CNPJ: | C13: =Planilha1!D10 -> 17.033.530/0004-81 | G13: Insc. Municipal: | I13: =Planilha1!J10 -> 0
A14: Endereço: | C14: =Planilha1!D12 -> RUA DO PASSEIO, 387 SAL 1501/1504 - CENTRO
A15: CEP.: | C15: =Planilha1!E13 -> 20.021-290 | G15: Cidade/UF: | I15: =Planilha1!H13 -> RIO DE JANEIRO/RJ
A16: Telefone: | C16: =Planilha1!E14 -> 0 | G16: E-mail: | I16: =Planilha1!H14 -> rio@nsshipping.com.br
A18: Descrição dos Serviços | K18: Valor R$
A19: Taxa de Administração com Vigias | K19: =Planilha1!J25 -> 2059.2081
A20: Navio: | B20: =Planilha1!D5 -> BANGLAR ARJAN
A21: Porto: | B21: =Planilha1!D6 -> RIO DE JANEIRO | E21: =Planilha1!D7 -> AO LARGO
A39: Sub Total R$ | K39: =SUM(K19:K38) -> 2059.2081
A40: Outros Créditos R$ | K40: 0
A41: Outros Débitos R$ | K41: 0
A42: Total R$ | K42: =SUM(K39:K41) -> 2059.2081
A44: OUTRAS INFORMAÇÕES

Sheet Planilha3
A1: SINDICATO DOS VIGIAS PORTUÁRIOS DO ESTADO DO RIO DE JANEIRO | I1: Nota de Débito Nº
A2: Rua Sacadura Cabral, 120 - salas 401 a 403 - Saúde - Rio de Janeiro/RJ | I2: =Planilha1!J1 -> 2900
A3: CEP.: 20081-262 | I3: Nat. da Op.: Repasse de Custo
A4: Tel.: (21) 2263-4430 | I4: Data de Emissão: | K4: =Planilha2!K2 -> 46266
K5: ,
A6: Destinatário: | C6: =Planilha1!D11 -> NORTH STAR SUDESTE SERVICOS MARITIMOS LTDA
A7: Endereço: | C7: =Planilha1!D12 -> RUA DO PASSEIO, 387 SAL 1501/1504 - CENTRO
A8: Município/RUF: | C8: =Planilha1!H13 -> RIO DE JANEIRO/RJ | I8: Cep.: | J8: =Planilha1!E13 -> 20.021-290
A9: Local de Pagamento: | C9: =C8 -> RIO DE JANEIRO/RJ
A10: CNPJ: | C10: =Planilha1!D10 -> 17.033.530/0004-81 | I10: Inscr. Mun.: | K10: =Planilha1!J10 -> 0
A12: Descrição das Cobranças | K12: Valor R$
A13: REPASSE CORRESPONDENTE AOS CUSTOS COM VIGIAS PORTUÁRIOS | K13: =Planilha1!J23 -> 2288.009
A14: NAVIO: | C14: =Planilha1!D5 -> BANGLAR ARJAN
A15: PORTO: | C15: =Planilha1!D6 -> RIO DE JANEIRO | E15: =Planilha1!D7 -> AO LARGO
A17: BENEFÍCIOS
A18: Vale Transporte | K18: =Planilha1!F28 -> 49.9
A19: Vale Refeção | K19: =Planilha1!I28 -> 68.45
A37: Total R$ | K37: =SUM(K13:K36) -> 2406.359
A39: Nota de Débito Nº | C39: Valor dos Serviços R$ | F39: ISS R$ | J39: Vencimento
A40: =I2 -> 2900 | C40: =K37 -> 2406.359 | F40: 0
A44: Declaramos que o Sindicato dos Vigias Portuários do Est. RJ, prestou os serviços constantes neste documento.
A46: Em,____/____/________
E47: Assinatura
E51: Sindicato dos Vigias Portuários do Estado do Rio de Janeiro
